dynamsoft_capture_vision_bundle/ConfusableChars.data
dynamsoft_capture_vision_bundle/OverlappingChars.data
dynamsoft_capture_vision_bundle/_DynamsoftBarcodeReader.cpython-312-darwin.so
dynamsoft_capture_vision_bundle/_DynamsoftCaptureVisionRouter.cpython-312-darwin.so
dynamsoft_capture_vision_bundle/_DynamsoftCodeParser.cpython-312-darwin.so
dynamsoft_capture_vision_bundle/_DynamsoftCodeParserDedicator.cpython-312-darwin.so
dynamsoft_capture_vision_bundle/_DynamsoftCore.cpython-312-darwin.so
dynamsoft_capture_vision_bundle/_DynamsoftDocumentNormalizer.cpython-312-darwin.so
dynamsoft_capture_vision_bundle/_DynamsoftImageProcessing.cpython-312-darwin.so
dynamsoft_capture_vision_bundle/_DynamsoftLabelRecognizer.cpython-312-darwin.so
dynamsoft_capture_vision_bundle/_DynamsoftLicense.cpython-312-darwin.so
dynamsoft_capture_vision_bundle/_DynamsoftNeuralNetwork.cpython-312-darwin.so
dynamsoft_capture_vision_bundle/_DynamsoftUtility.cpython-312-darwin.so
dynamsoft_capture_vision_bundle/__init__.py
dynamsoft_capture_vision_bundle/core.py
dynamsoft_capture_vision_bundle/cvr.py
dynamsoft_capture_vision_bundle/dbr.py
dynamsoft_capture_vision_bundle/dcp.py
dynamsoft_capture_vision_bundle/dcpd.py
dynamsoft_capture_vision_bundle/ddn.py
dynamsoft_capture_vision_bundle/dip.py
dynamsoft_capture_vision_bundle/dlr.py
dynamsoft_capture_vision_bundle/dnn.py
dynamsoft_capture_vision_bundle/libDynamicPdf.dylib
dynamsoft_capture_vision_bundle/libDynamsoftBarcodeReader.dylib
dynamsoft_capture_vision_bundle/libDynamsoftCaptureVisionRouter.dylib
dynamsoft_capture_vision_bundle/libDynamsoftCodeParser.dylib
dynamsoft_capture_vision_bundle/libDynamsoftCodeParserDedicator.dylib
dynamsoft_capture_vision_bundle/libDynamsoftCore.dylib
dynamsoft_capture_vision_bundle/libDynamsoftDocumentNormalizer.dylib
dynamsoft_capture_vision_bundle/libDynamsoftImageProcessing.dylib
dynamsoft_capture_vision_bundle/libDynamsoftLabelRecognizer.dylib
dynamsoft_capture_vision_bundle/libDynamsoftLicense.dylib
dynamsoft_capture_vision_bundle-3.2.5000.dist-info/licenses/LICENSE.txt
dynamsoft_capture_vision_bundle-3.2.5000.dist-info/METADATA
dynamsoft_capture_vision_bundle-3.2.5000.dist-info/WHEEL
dynamsoft_capture_vision_bundle-3.2.5000.dist-info/top_level.txt
dynamsoft_capture_vision_bundle-3.2.5000.dist-info/RECORD
